{"items":[{"idName":"FavitesRotundata","position":{"x":175.5659,"y":-0.4547716,"z":497.9171},"rotation":{"x":0,"y":0.7003039,"z":0,"w":-0.7138449},"scale":{"x":1.047297,"y":1.047297,"z":1.047297}},{"idName":"SwiftiaExserta","position":{"x":178.8518,"y":-1.429949,"z":496.4275},"rotation":{"x":0,"y":0.8268905,"z":0,"w":-0.5623629},"scale":{"x":1.165183,"y":1.165183,"z":1.165183}},{"idName":"AnnellaMollis","position":{"x":175.1716,"y":-0.6196176,"z":476.0393},"rotation":{"x":0,"y":0.4142347,"z":0,"w":-0.9101701},"scale":{"x":1.052335,"y":1.052335,"z":1.052335}},{"idName":"EunicellaCavolini","position":{"x":177.9215,"y":-0.6775384,"z":498.2907},"rotation":{"x":0,"y":0.6264742,"z":0,"w":0.7794422},"scale":{"x":1.509072,"y":1.509072,"z":1.509072}},{"idName":"TurbinariaPeltata","position":{"x":185.6284,"y":-1.393206,"z":476.7425},"rotation":{"x":0.1990599,"y":-0.09886034,"z":0.02018831,"w":0.9747791},"scale":{"x":1.001882,"y":1.001882,"z":1.001882}},{"idName":"AcroporaCervicornis","position":{"x":181.8237,"y":-1.23104,"z":499.6241},"rotation":{"x":0,"y":0.8272152,"z":0,"w":-0.5618854},"scale":{"x":1.818281,"y":1.818279,"z":1.818281}},{"idName":"AcroporaCervicornis","position":{"x":178.9436,"y":-1.384673,"z":494.4386},"rotation":{"x":0,"y":0.7111654,"z":0,"w":0.7030247},"scale":{"x":1.324049,"y":1.324049,"z":1.324049}},{"idName":"SarcophytonElegans","position":{"x":180.2132,"y":-1.21738,"z":496.2881},"rotation":{"x":0.1440293,"y":0.6710758,"z":-0.1352617,"w":0.7145748},"scale":{"x":1.232137,"y":1.232137,"z":1.232137}},{"idName":"SwiftiaExserta","position":{"x":188.2269,"y":-1.755632,"z":477.2927},"rotation":{"x":0,"y":0.276322,"z":0,"w":0.9610651},"scale":{"x":2.089274,"y":2.089274,"z":2.089274}},{"idName":"EunicellaCavolini","position":{"x":178.3416,"y":-1.573746,"z":495.9026},"rotation":{"x":0,"y":0.8360497,"z":0,"w":0.5486537},"scale":{"x":1.638365,"y":1.638365,"z":1.638365}},{"idName":"GorgoniaFlabellum","position":{"x":186.2841,"y":-1.218156,"z":476.4576},"rotation":{"x":0,"y":0.8289201,"z":0,"w":0.559367},"scale":{"x":1.980563,"y":1.980563,"z":1.980563}},{"idName":"PoritesProfundus","position":{"x":182.1756,"y":-1.32116,"z":476.9918},"rotation":{"x":0,"y":0.08342436,"z":0,"w":0.9965141},"scale":{"x":1.307982,"y":1.307982,"z":1.307982}},{"idName":"AcroporaCervicornis","position":{"x":179.8741,"y":-1.121348,"z":498.0297},"rotation":{"x":0,"y":0.9626498,"z":0,"w":-0.2707498},"scale":{"x":1.492538,"y":1.492538,"z":1.492538}},{"idName":"PocilloporaVerrucosa","position":{"x":188.5075,"y":-1.879647,"z":476.2341},"rotation":{"x":0.08637067,"y":0.756348,"z":-0.1020137,"w":0.6403679},"scale":{"x":0.8749121,"y":0.8749119,"z":0.8749121}},{"idName":"AnnellaMollis","position":{"x":185.9605,"y":-1.675587,"z":477.4869},"rotation":{"x":0,"y":0.9749523,"z":0,"w":0.2224141},"scale":{"x":1.350146,"y":1.350147,"z":1.350146}},{"idName":"PoritesNodifera","position":{"x":176.3527,"y":-0.5133271,"z":475.5124},"rotation":{"x":0.2425584,"y":0.1685645,"z":-0.04283936,"w":0.9544194},"scale":{"x":2.570827,"y":2.570827,"z":2.570827}},{"idName":"AcroporaBushyensis","position":{"x":179.4251,"y":-1.591938,"z":476.7655},"rotation":{"x":0.2803941,"y":-0.0004094232,"z":0.0001195975,"w":0.9598849},"scale":{"x":1.552395,"y":1.552396,"z":1.552396}},{"idName":"PoritesProfundus","position":{"x":176.4042,"y":-1.330279,"z":495.4869},"rotation":{"x":0,"y":0.8900478,"z":0,"w":-0.4558673},"scale":{"x":1.919006,"y":1.919005,"z":1.919006}},{"idName":"HelioporaCoerulea","position":{"x":180.5108,"y":-1.373527,"z":497.4776},"rotation":{"x":0,"y":0.967969,"z":0,"w":0.2510698},"scale":{"x":1.633412,"y":1.633412,"z":1.633412}},{"idName":"AcroporaCaroliniana","position":{"x":178.2118,"y":-1.413182,"z":476.6787},"rotation":{"x":0.2380459,"y":0.1186592,"z":-0.02931539,"w":0.9635325},"scale":{"x":3.017952,"y":3.017952,"z":3.017952}},{"idName":"TurbinariaPeltata","position":{"x":177.4842,"y":-0.9673536,"z":496.7404},"rotation":{"x":0.0548331,"y":0.9448084,"z":-0.2413929,"w":0.2146161},"scale":{"x":1.149969,"y":1.149969,"z":1.14997}},{"idName":"HelioporaCoerulea","position":{"x":180.5016,"y":-0.9562373,"z":475.9251},"rotation":{"x":0,"y":0.7533951,"z":0,"w":0.6575682},"scale":{"x":1.959313,"y":1.959313,"z":1.959313}},{"idName":"AnnellaMollis","position":{"x":179.6955,"y":-0.5309963,"z":475.1047},"rotation":{"x":0,"y":0.03782601,"z":0,"w":-0.9992843},"scale":{"x":1.958004,"y":1.958004,"z":1.958004}},{"idName":"PodabaciaCrustacea","position":{"x":184.7585,"y":-1.226853,"z":476.3484},"rotation":{"x":0,"y":0.8328655,"z":0,"w":0.5534755},"scale":{"x":2.578712,"y":2.578712,"z":2.578712}},{"idName":"PoritesNodifera","position":{"x":187.7507,"y":-1.679643,"z":476.1222},"rotation":{"x":0.08637067,"y":0.756348,"z":-0.1020137,"w":0.6403679},"scale":{"x":1.14126,"y":1.14126,"z":1.14126}},{"idName":"AcroporaCaroliniana","position":{"x":184.3942,"y":-2.290436,"z":499.3416},"rotation":{"x":0.2153737,"y":-0.3379158,"z":0.0797371,"w":0.9127262},"scale":{"x":2.66288,"y":2.66288,"z":2.662881}},{"idName":"PodabaciaCrustacea","position":{"x":180.4145,"y":-1.298724,"z":496.1709},"rotation":{"x":0,"y":0.7646399,"z":0,"w":-0.6444578},"scale":{"x":1.611402,"y":1.611401,"z":1.611402}},{"idName":"DiploriaStrigosa","position":{"x":175.4477,"y":-1.133273,"z":476.8728},"rotation":{"x":0.2615502,"y":0.09905643,"z":-0.02699579,"w":0.9597138},"scale":{"x":2.991148,"y":2.991148,"z":2.991148}},{"idName":"AcroporaHumilis","position":{"x":181.8764,"y":-1.630692,"z":498.338},"rotation":{"x":0.1033583,"y":0.8834908,"z":-0.2319851,"w":0.3936292},"scale":{"x":1.150129,"y":1.150129,"z":1.150129}},{"idName":"PodabaciaCrustacea","position":{"x":177.636,"y":-0.6233311,"z":497.715},"rotation":{"x":0,"y":0.3762282,"z":0,"w":0.926527},"scale":{"x":1.417567,"y":1.417567,"z":1.417567}},{"idName":"AcalycigorgiaInermis","position":{"x":179.0839,"y":-1.888864,"z":493.1177},"rotation":{"x":0,"y":0.5562604,"z":0,"w":-0.831008},"scale":{"x":0.9573985,"y":0.9573987,"z":0.9573985}},{"idName":"SwiftiaExserta","position":{"x":178.7515,"y":-1.558826,"z":476.829},"rotation":{"x":0,"y":0.6562049,"z":0,"w":-0.7545828},"scale":{"x":1.540248,"y":1.540249,"z":1.540248}},{"idName":"AnnellaMollis","position":{"x":179.3536,"y":-0.9955877,"z":498.4669},"rotation":{"x":0,"y":0.2866684,"z":0,"w":0.9580299},"scale":{"x":1.596193,"y":1.596193,"z":1.596193}},{"idName":"FavitesRotundata","position":{"x":186.9558,"y":-1.48969,"z":477.2457},"rotation":{"x":0,"y":0.9897692,"z":0,"w":0.1426782},"scale":{"x":0.9935933,"y":0.9935929,"z":0.9935933}},{"idName":"PoritesNodifera","position":{"x":182.9122,"y":-2.155462,"z":497.7141},"rotation":{"x":0.2153737,"y":-0.3379158,"z":0.0797371,"w":0.9127262},"scale":{"x":3.296705,"y":3.296706,"z":3.296706}},{"idName":"GorgoniaFlabellum","position":{"x":180.7222,"y":-1.908991,"z":477.4846},"rotation":{"x":0,"y":0.9711095,"z":0,"w":-0.2386345},"scale":{"x":1.631882,"y":1.631881,"z":1.631882}},{"idName":"AnnellaMollis","position":{"x":178.6479,"y":-1.058193,"z":475.9292},"rotation":{"x":0,"y":0.006397285,"z":0,"w":0.9999796},"scale":{"x":1.47777,"y":1.47777,"z":1.47777}},{"idName":"AcroporaCervicornis","position":{"x":180.8555,"y":-1.00321,"z":476.1075},"rotation":{"x":0,"y":0.8964069,"z":0,"w":0.443232},"scale":{"x":1.593034,"y":1.593034,"z":1.593034}},{"idName":"DistichoporaViolacea","position":{"x":175.3524,"y":-0.7964702,"z":476.3084},"rotation":{"x":0,"y":0.9246029,"z":0,"w":-0.3809325},"scale":{"x":1.536877,"y":1.536877,"z":1.536877}},{"idName":"FavitesRotundata","position":{"x":186.5984,"y":-1.301966,"z":475.451},"rotation":{"x":0,"y":0.8444806,"z":0,"w":0.5355862},"scale":{"x":0.9817489,"y":0.981749,"z":0.9817489}},{"idName":"AcroporaCervicornis","position":{"x":179.6713,"y":-1.212876,"z":495.839},"rotation":{"x":0,"y":0.08831108,"z":0,"w":-0.996093},"scale":{"x":1.753615,"y":1.753615,"z":1.753615}},{"idName":"AcroporaCaroliniana","position":{"x":182.7436,"y":-0.9415952,"z":476.3656},"rotation":{"x":0.2574725,"y":0.06527255,"z":-0.01743493,"w":0.9639209},"scale":{"x":2.364774,"y":2.364775,"z":2.364775}},{"idName":"EunicellaCavolini","position":{"x":184.9149,"y":-0.94516,"z":475.5876},"rotation":{"x":0,"y":0.05680721,"z":0,"w":0.9983852},"scale":{"x":1.853741,"y":1.853741,"z":1.853741}},{"idName":"PocilloporaVerrucosa","position":{"x":177.313,"y":-0.5508435,"z":499.5525},"rotation":{"x":0.02230887,"y":0.7811792,"z":-0.02796047,"w":0.6232813},"scale":{"x":1.126213,"y":1.126213,"z":1.126213}},{"idName":"PodabaciaCrustacea","position":{"x":175.4675,"y":-0.546728,"z":497.2178},"rotation":{"x":0,"y":0.1830178,"z":0,"w":0.9831097},"scale":{"x":0.5689914,"y":0.5689914,"z":0.5689914}},{"idName":"HelioporaCoerulea","position":{"x":176.129,"y":-0.4260371,"z":499.0952},"rotation":{"x":0,"y":0.05875555,"z":0,"w":-0.9982724},"scale":{"x":1.363852,"y":1.363852,"z":1.363852}},{"idName":"DistichoporaViolacea","position":{"x":181.4711,"y":-1.607757,"z":497.9482},"rotation":{"x":0,"y":0.4656829,"z":0,"w":-0.8849517},"scale":{"x":1.450124,"y":1.450124,"z":1.450124}},{"idName":"PocilloporaVerrucosa","position":{"x":178.5981,"y":-1.786464,"z":477.3133},"rotation":{"x":0.2380459,"y":0.1186592,"z":-0.02931539,"w":0.9635325},"scale":{"x":0.7794524,"y":0.7794524,"z":0.7794524}},{"idName":"PoritesProfundus","position":{"x":175.027,"y":-1.444068,"z":477.5267},"rotation":{"x":0,"y":0.6266565,"z":0,"w":-0.7792956},"scale":{"x":1.44004,"y":1.44004,"z":1.44004}},{"idName":"PoritesProfundus","position":{"x":178.1153,"y":-0.7163624,"z":498.5536},"rotation":{"x":0,"y":0.2247639,"z":0,"w":0.9744133},"scale":{"x":1.411442,"y":1.411442,"z":1.411442}},{"idName":"PodabaciaCrustacea","position":{"x":178.4209,"y":-1.512828,"z":476.8216},"rotation":{"x":0,"y":0.8682563,"z":0,"w":-0.496116},"scale":{"x":2.696292,"y":2.696292,"z":2.696292}},{"idName":"PodabaciaCrustacea","position":{"x":176.5279,"y":-1.651327,"z":492.5566},"rotation":{"x":0,"y":0.9501789,"z":0,"w":0.3117051},"scale":{"x":1.413622,"y":1.413622,"z":1.413622}},{"idName":"PoritesNodifera","position":{"x":176.2388,"y":-0.6426353,"z":497.0893},"rotation":{"x":0.01688273,"y":0.9815566,"z":-0.1596475,"w":0.1037996},"scale":{"x":2.616191,"y":2.61619,"z":2.616191}},{"idName":"AnnellaMollis","position":{"x":179.1567,"y":-0.9321741,"z":499.5163},"rotation":{"x":0,"y":0.3110775,"z":0,"w":0.9503846},"scale":{"x":1.494681,"y":1.494681,"z":1.494681}},{"idName":"AcroporaHyacinthus","position":{"x":180.3036,"y":-0.6502367,"z":475.3851},"rotation":{"x":0.2870926,"y":-0.1423162,"z":0.04317706,"w":0.9462873},"scale":{"x":1.370148,"y":1.370148,"z":1.370148}},{"idName":"AcalycigorgiaInermis","position":{"x":178.6603,"y":-1.437472,"z":476.6141},"rotation":{"x":0,"y":0.4359947,"z":0,"w":-0.8999493},"scale":{"x":0.6367717,"y":0.6367717,"z":0.6367717}},{"idName":"PoritesProfundus","position":{"x":178.0699,"y":-1.633762,"z":494.2197},"rotation":{"x":0,"y":0.7759473,"z":0,"w":-0.6307977},"scale":{"x":2.035532,"y":2.035532,"z":2.035532}},{"idName":"SwiftiaExserta","position":{"x":179.3254,"y":-2.239848,"z":492.6436},"rotation":{"x":0,"y":0.5473745,"z":0,"w":0.8368878},"scale":{"x":1.659951,"y":1.65995,"z":1.659951}},{"idName":"PocilloporaVerrucosa","position":{"x":175.8064,"y":-0.4320484,"z":498.5802},"rotation":{"x":0.04875683,"y":0.8809512,"z":-0.09309338,"w":0.4613906},"scale":{"x":1.109299,"y":1.109299,"z":1.109299}},{"idName":"PoritesProfundus","position":{"x":175.3884,"y":-1.417331,"z":477.3781},"rotation":{"x":0,"y":0.6573163,"z":0,"w":-0.7536148},"scale":{"x":1.556389,"y":1.556389,"z":1.556389}},{"idName":"HelioporaCoerulea","position":{"x":177.9931,"y":-1.704549,"z":492.8337},"rotation":{"x":0,"y":0.8403417,"z":0,"w":-0.542057},"scale":{"x":1.100305,"y":1.100305,"z":1.100305}},{"idName":"DiploriaStrigosa","position":{"x":177.2357,"y":-1.673618,"z":477.4373},"rotation":{"x":0.2615502,"y":0.09905643,"z":-0.02699579,"w":0.9597138},"scale":{"x":3.40045,"y":3.400451,"z":3.400451}},{"idName":"PocilloporaVerrucosa","position":{"x":176.5627,"y":-1.234411,"z":495.7572},"rotation":{"x":0.0548331,"y":0.9448084,"z":-0.2413929,"w":0.2146161},"scale":{"x":0.9927203,"y":0.9927197,"z":0.9927205}},{"idName":"AnnellaMollis","position":{"x":177.0776,"y":-0.5664899,"z":497.5357},"rotation":{"x":0,"y":0.1040032,"z":0,"w":0.994577},"scale":{"x":1.511398,"y":1.511398,"z":1.511398}},{"idName":"AcroporaRobusta","position":{"x":179.121,"y":-0.9898225,"z":497.4433},"rotation":{"x":0,"y":0.8240677,"z":0,"w":0.5664914},"scale":{"x":1.643555,"y":1.643555,"z":1.643555}},{"idName":"DiploriaStrigosa","position":{"x":185.2188,"y":-1.692732,"z":477.376},"rotation":{"x":0.1990599,"y":-0.09886034,"z":0.02018831,"w":0.9747791},"scale":{"x":1.382699,"y":1.382698,"z":1.382698}},{"idName":"AcroporaCaroliniana","position":{"x":177.4806,"y":-1.737441,"z":478.1742},"rotation":{"x":0.0418353,"y":0.7135207,"z":-0.04276089,"w":0.6980755},"scale":{"x":2.232373,"y":2.232373,"z":2.232372}},{"idName":"AcalycigorgiaInermis","position":{"x":176.9048,"y":-1.481672,"z":477.1733},"rotation":{"x":0,"y":0.3391199,"z":0,"w":0.9407431},"scale":{"x":0.9156854,"y":0.9156854,"z":0.9156854}},{"idName":"AcalycigorgiaInermis","position":{"x":180.3328,"y":-1.24137,"z":495.1727},"rotation":{"x":0,"y":0.9999949,"z":0,"w":0.00319476},"scale":{"x":1.07527,"y":1.07527,"z":1.07527}},{"idName":"SarcophytonElegans","position":{"x":178.0912,"y":-1.446212,"z":496.0469},"rotation":{"x":0.05229314,"y":0.9471285,"z":-0.2402013,"w":0.2061951},"scale":{"x":1.336457,"y":1.336457,"z":1.336457}},{"idName":"AcalycigorgiaInermis","position":{"x":179.2815,"y":-0.9659053,"z":499.1625},"rotation":{"x":0,"y":0.9789816,"z":0,"w":0.2039489},"scale":{"x":0.9872559,"y":0.9872556,"z":0.9872559}},{"idName":"DiploriaStrigosa","position":{"x":177.1746,"y":-0.5487515,"z":499.0765},"rotation":{"x":0.02230887,"y":0.7811792,"z":-0.02796047,"w":0.6232813},"scale":{"x":1.264329,"y":1.264329,"z":1.264329}},{"idName":"FavitesRotundata","position":{"x":181.1445,"y":-1.60143,"z":495.7083},"rotation":{"x":0,"y":0.6625116,"z":0,"w":-0.7490517},"scale":{"x":0.7828203,"y":0.7828201,"z":0.7828203}},{"idName":"PocilloporaVerrucosa","position":{"x":188.2837,"y":-1.828133,"z":476.0328},"rotation":{"x":0.08637067,"y":0.756348,"z":-0.1020137,"w":0.6403679},"scale":{"x":0.7756803,"y":0.7756799,"z":0.7756802}},{"idName":"PodabaciaCrustacea","position":{"x":182.6479,"y":-1.688142,"z":499.0481},"rotation":{"x":0,"y":0.9790915,"z":0,"w":0.2034207},"scale":{"x":0.5798498,"y":0.5798496,"z":0.5798498}},{"idName":"AcroporaBushyensis","position":{"x":179.7809,"y":-0.8181698,"z":475.5544},"rotation":{"x":0.2803941,"y":-0.0004094232,"z":0.0001195975,"w":0.9598849},"scale":{"x":1.102161,"y":1.102161,"z":1.102161}},{"idName":"AcroporaCaroliniana","position":{"x":175.8633,"y":-1.011229,"z":495.8809},"rotation":{"x":0.01688273,"y":0.9815566,"z":-0.1596475,"w":0.1037996},"scale":{"x":3.054126,"y":3.054126,"z":3.054127}},{"idName":"AcroporaHyacinthus","position":{"x":176.919,"y":-0.5190048,"z":499.4717},"rotation":{"x":0.04875683,"y":0.8809512,"z":-0.09309338,"w":0.4613906},"scale":{"x":1.920024,"y":1.920024,"z":1.920024}},{"idName":"EunicellaCavolini","position":{"x":175.5407,"y":-0.7537588,"z":496.5999},"rotation":{"x":0,"y":0.2821746,"z":0,"w":0.9593631},"scale":{"x":2.11167,"y":2.11167,"z":2.11167}},{"idName":"AcroporaHyacinthus","position":{"x":186.1601,"y":-1.147091,"z":475.22},"rotation":{"x":0.1198251,"y":0.7357885,"z":-0.1350799,"w":0.6526949},"scale":{"x":1.44514,"y":1.445139,"z":1.44514}},{"idName":"GorgoniaFlabellum","position":{"x":179.7876,"y":-2.205447,"z":492.9587},"rotation":{"x":0,"y":0.9985266,"z":0,"w":-0.05426582},"scale":{"x":1.34805,"y":1.348049,"z":1.34805}},{"idName":"SwiftiaExserta","position":{"x":178.721,"y":-0.9983307,"z":475.8355},"rotation":{"x":0,"y":0.1805043,"z":0,"w":-0.9835742},"scale":{"x":1.909545,"y":1.909546,"z":1.909545}},{"idName":"HelioporaCoerulea","position":{"x":189.4338,"y":-1.992482,"z":476.7415},"rotation":{"x":0,"y":0.6643749,"z":0,"w":0.7473995},"scale":{"x":1.551494,"y":1.551494,"z":1.551494}},{"idName":"HelioporaCoerulea","position":{"x":177.5635,"y":-1.770646,"z":493.8837},"rotation":{"x":0,"y":0.9821428,"z":0,"w":0.1881369},"scale":{"x":1.37376,"y":1.37376,"z":1.37376}},{"idName":"PoritesNodifera","position":{"x":189.5498,"y":-2.124535,"z":477.0634},"rotation":{"x":0.08637067,"y":0.756348,"z":-0.1020137,"w":0.6403679},"scale":{"x":2.881192,"y":2.881191,"z":2.881192}},{"idName":"AcroporaRobusta","position":{"x":178.3332,"y":-0.7547267,"z":499.1821},"rotation":{"x":0,"y":0.688618,"z":0,"w":-0.7251243},"scale":{"x":1.559855,"y":1.559855,"z":1.559855}},{"idName":"AcroporaHyacinthus","position":{"x":178.8483,"y":-0.894241,"z":497.8186},"rotation":{"x":0.07505371,"y":0.7321357,"z":-0.0817633,"w":0.6720558},"scale":{"x":1.212713,"y":1.212713,"z":1.212713}},{"idName":"AcroporaHumilis","position":{"x":189.0847,"y":-2.002461,"z":476.5526},"rotation":{"x":0.2721433,"y":-0.2535773,"z":0.07458515,"w":0.9252425},"scale":{"x":1.493427,"y":1.493427,"z":1.493426}},{"idName":"TurbinariaPeltata","position":{"x":182.2526,"y":-1.852487,"z":498.1683},"rotation":{"x":0.1033583,"y":0.8834908,"z":-0.2319851,"w":0.3936292},"scale":{"x":0.8020864,"y":0.8020862,"z":0.8020862}},{"idName":"AcroporaBushyensis","position":{"x":179.3067,"y":-1.901634,"z":493.2188},"rotation":{"x":0.07185415,"y":0.9273773,"z":-0.278482,"w":0.2392827},"scale":{"x":1.717733,"y":1.717733,"z":1.717733}},{"idName":"AcroporaRobusta","position":{"x":175.8483,"y":-1.541277,"z":478.1227},"rotation":{"x":0,"y":0.9227061,"z":0,"w":-0.3855042},"scale":{"x":1.448253,"y":1.448253,"z":1.448253}},{"idName":"AcroporaHumilis","position":{"x":179.903,"y":-1.095431,"z":499.7078},"rotation":{"x":0.07505371,"y":0.7321357,"z":-0.0817633,"w":0.6720558},"scale":{"x":1.535996,"y":1.535997,"z":1.535997}},{"idName":"AcroporaHyacinthus","position":{"x":176.1763,"y":-1.229671,"z":476.8881},"rotation":{"x":0.2615502,"y":0.09905643,"z":-0.02699579,"w":0.9597138},"scale":{"x":1.907709,"y":1.90771,"z":1.907709}},{"idName":"PodabaciaCrustacea","position":{"x":178.716,"y":-0.8339704,"z":499.5415},"rotation":{"x":0,"y":0.8960925,"z":0,"w":0.4438674},"scale":{"x":0.7536725,"y":0.7536721,"z":0.7536725}},{"idName":"PocilloporaVerrucosa","position":{"x":177.6905,"y":-1.479936,"z":495.7953},"rotation":{"x":0.05229314,"y":0.9471285,"z":-0.2402013,"w":0.2061951},"scale":{"x":1.124719,"y":1.124719,"z":1.124719}},{"idName":"GorgoniaFlabellum","position":{"x":175.6697,"y":-0.3629132,"z":498.9509},"rotation":{"x":0,"y":0.6982958,"z":0,"w":0.7158093},"scale":{"x":1.803673,"y":1.803673,"z":1.803673}},{"idName":"AcroporaBushyensis","position":{"x":177.0392,"y":-0.9772971,"z":496.507},"rotation":{"x":0.0548331,"y":0.9448084,"z":-0.2413929,"w":0.2146161},"scale":{"x":1.618081,"y":1.61808,"z":1.618081}},{"idName":"AcroporaHumilis","position":{"x":176.8178,"y":-0.5251363,"z":498.9934},"rotation":{"x":0.02230887,"y":0.7811792,"z":-0.02796047,"w":0.6232813},"scale":{"x":1.773516,"y":1.773516,"z":1.773516}},{"idName":"SwiftiaExserta","position":{"x":177.0377,"y":-1.715055,"z":495.0099},"rotation":{"x":0,"y":0.7557434,"z":0,"w":-0.6548679},"scale":{"x":1.237559,"y":1.237559,"z":1.237559}},{"idName":"SarcophytonElegans","position":{"x":183.4496,"y":-2.009974,"z":497.7917},"rotation":{"x":0.2153737,"y":-0.3379158,"z":0.0797371,"w":0.9127262},"scale":{"x":1.512595,"y":1.512596,"z":1.512596}},{"idName":"PoritesNodifera","position":{"x":182.4607,"y":-1.413728,"z":499.5629},"rotation":{"x":0.1033583,"y":0.8834908,"z":-0.2319851,"w":0.3936292},"scale":{"x":2.228946,"y":2.228945,"z":2.228945}},{"idName":"SwiftiaExserta","position":{"x":177.9397,"y":-1.700993,"z":495.0411},"rotation":{"x":0,"y":0.9673851,"z":0,"w":0.2533105},"scale":{"x":1.885,"y":1.884999,"z":1.885}},{"idName":"HelioporaCoerulea","position":{"x":189.0905,"y":-1.374368,"z":475.4222},"rotation":{"x":0,"y":0.230384,"z":0,"w":0.9730998},"scale":{"x":2.056169,"y":2.056169,"z":2.056169}}]}
